icx/__init__.py
icx/app.py
icx/construct_graph.py
icx/dashboard.py
icx/functions.py
icx/Datasets/adult.csv
icx/Datasets/compas.csv
icx/Datasets/german.csv
icx-1.0.2.dist-info/METADATA
icx-1.0.2.dist-info/WHEEL
icx-1.0.2.dist-info/licenses/LICENSE.md
icx-1.0.2.dist-info/RECORD
