Metadata-Version: 2.4
Name: icx
Version: 1.0.2
Summary: This package provides the functionality for an interactive Streamlit dashboard designed to support stakeholders in exploring individual fairness notions within algorithmic decision-making systems. 
Project-URL: Homepage, https://github.com/maddiewaller/Individual-Consistency-eXplorer/
Author-email: Madeleine Waller <madeleine.waller@kcl.ac.uk>
License-Expression: MIT
License-File: LICENSE.md
Classifier: Operating System :: OS Independent
Classifier: Programming Language :: Python :: 3
Requires-Python: >=3.0
Requires-Dist: gower
Requires-Dist: numpy
Requires-Dist: pandas
Requires-Dist: scikit-learn
Requires-Dist: streamlit
Requires-Dist: streamlit-aggrid
Requires-Dist: streamlit-sortables
